rolling_king/__init__.py
rolling_king/autotest/__init__.py
rolling_king/autotest/conf/__init__.py
rolling_king/autotest/conf/db_conf.py
rolling_king/autotest/db/__init__.py
rolling_king/autotest/db/db_models.py
rolling_king/autotest/db/db_util.py
rolling_king/autotest/db/sqlalchemy_util.py
rolling_king/autotest/requests/__init__.py
rolling_king/autotest/requests/http_sender_module.py
rolling_king/autotest/tests/__init__.py
rolling_king/autotest/tests/base/__init__.py
rolling_king/autotest/tests/base/autotest_generator.py
rolling_king/autotest/tests/base/base_compare.py
rolling_king/autotest/tests/base/base_conftest.py
rolling_king/autotest/tests/base/base_test.py
rolling_king/jason/__init__.py
rolling_king/jason/ai/__init__.py
rolling_king/jason/ai/zhipu.py
rolling_king/jason/autogen/__init__.py
rolling_king/jason/autogen/auto_generate.py
rolling_king/jason/crawler/TempBaidu.py
rolling_king/jason/crawler/__init__.py
rolling_king/jason/crawler/crawler_urllib.py
rolling_king/jason/crawler/crawler_weibo.py
rolling_king/jason/gitlab/__init__.py
rolling_king/jason/gitlab/gitlab_utils.py
rolling_king/jason/newcore/__init__.py
rolling_king/jason/newcore/test_ccc.py
rolling_king/jason/openpyxl/__init__.py
rolling_king/jason/openpyxl/excel_util.py
rolling_king/jason/playwright/__init__.py
rolling_king/jason/playwright/playwright_51job.py
rolling_king/jason/playwright/playwright_common.py
rolling_king/jason/playwright/test_generate.py
rolling_king/jason/playwright/test_playwright.py
rolling_king/jason/pypac/__init__.py
rolling_king/jason/pypac/pyfile1.py
rolling_king/jason/pypac/pyfile2.py
rolling_king/jason/pypac/test.py
rolling_king/jason/pytest/__init__.py
rolling_king/jason/pytest/conftest.py
rolling_king/jason/pytest/test_class.py
rolling_king/jason/pytest/test_sample.py
rolling_king/jason/python/ClassTest.py
rolling_king/jason/python/DbTest.py
rolling_king/jason/python/MailTest.py
rolling_king/jason/python/MyPyTest.py
rolling_king/jason/python/PythonTest.py
51job_autotest_framework-0.3.8.dist-info/LICENSE
51job_autotest_framework-0.3.8.dist-info/METADATA
51job_autotest_framework-0.3.8.dist-info/WHEEL
51job_autotest_framework-0.3.8.dist-info/top_level.txt
51job_autotest_framework-0.3.8.dist-info/RECORD
